Workbook

Sheet Lisez-moi
A1: Suivi de la campagne de recette fonctionnelle YABA
A3: Cellules à remplir : fond jaune pâle dans « Cas de test » (Testeur, Date, Statut, N° anomalie, Commentaire) et dans « Anomalies ».
A4: Statut : liste déroulante OK / KO / Bloqué / NT.
A5: Date : saisir au format JJ/MM/AAAA.
A6: Un KO porte toujours un numéro d'anomalie (ANO-001…) détaillé dans l'onglet « Anomalies ».
A7: L'onglet « Synthèse » se calcule automatiquement à partir des statuts saisis.
A8: Étapes détaillées, comptes de test et critères de sortie : voir le cahier de recette (Word).
A10: Exemple de ligne remplie : Testeur « A. Kouassi », Date 29/09/2026, Statut KO, N° anomalie ANO-004, Commentaire « export Excel vide ».

Sheet Synthèse
A1: Synthèse de la campagne
A3: Catégorie | B3: Total | C3: OK | D3: KO | E3: Bloqué | F3: NT | G3: Non renseigné | H3: % exécuté | I3: % OK
A4: Transverse | B4: =COUNTIF('Cas de test'!$A$2:$A$140,"Transverse") | C4: =COUNTIFS('Cas de test'!$A$2:$A$140,"Transverse",'Cas de test'!$J$2:$J$140,"OK") | D4: =COUNTIFS('Cas de test'!$A$2:$A$140,"Transverse",'Cas de test'!$J$2:$J$140,"KO") | E4: =COUNTIFS('Cas de test'!$A$2:$A$140,"Transverse",'Cas de test'!$J$2:$J$140,"Bloqué") | F4: =COUNTIFS('Cas de test'!$A$2:$A$140,"Transverse",'Cas de test'!$J$2:$J$140,"NT") | G4: =B4-SUM(C4:F4) | H4: =IF(B4=0,0,SUM(C4:E4)/B4) | I4: =IF(B4=0,0,C4/B4)
A5: Parcours rôle | B5: =COUNTIF('Cas de test'!$A$2:$A$140,"Parcours rôle") | C5: =COUNTIFS('Cas de test'!$A$2:$A$140,"Parcours rôle",'Cas de test'!$J$2:$J$140,"OK") | D5: =COUNTIFS('Cas de test'!$A$2:$A$140,"Parcours rôle",'Cas de test'!$J$2:$J$140,"KO") | E5: =COUNTIFS('Cas de test'!$A$2:$A$140,"Parcours rôle",'Cas de test'!$J$2:$J$140,"Bloqué") | F5: =COUNTIFS('Cas de test'!$A$2:$A$140,"Parcours rôle",'Cas de test'!$J$2:$J$140,"NT") | G5: =B5-SUM(C5:F5) | H5: =IF(B5=0,0,SUM(C5:E5)/B5) | I5: =IF(B5=0,0,C5/B5)
A6: Bout en bout | B6: =COUNTIF('Cas de test'!$A$2:$A$140,"Bout en bout") | C6: =COUNTIFS('Cas de test'!$A$2:$A$140,"Bout en bout",'Cas de test'!$J$2:$J$140,"OK") | D6: =COUNTIFS('Cas de test'!$A$2:$A$140,"Bout en bout",'Cas de test'!$J$2:$J$140,"KO") | E6: =COUNTIFS('Cas de test'!$A$2:$A$140,"Bout en bout",'Cas de test'!$J$2:$J$140,"Bloqué") | F6: =COUNTIFS('Cas de test'!$A$2:$A$140,"Bout en bout",'Cas de test'!$J$2:$J$140,"NT") | G6: =B6-SUM(C6:F6) | H6: =IF(B6=0,0,SUM(C6:E6)/B6) | I6: =IF(B6=0,0,C6/B6)
A7: TOTAL | B7: =SUM(B4:B6) | C7: =SUM(C4:C6) | D7: =SUM(D4:D6) | E7: =SUM(E4:E6) | F7: =SUM(F4:F6) | G7: =SUM(G4:G6) | H7: =IF(B7=0,0,SUM(C7:E7)/B7) | I7: =IF(B7=0,0,C7/B7)
A10: Anomalies non fermées
A11: Bloquante | B11: =COUNTIFS(Anomalies!$E$2:$E$101,"Bloquante",Anomalies!$J$2:$J$101,"<>Fermée",Anomalies!$J$2:$J$101,"<>Vérifiée")
A12: Majeure | B12: =COUNTIFS(Anomalies!$E$2:$E$101,"Majeure",Anomalies!$J$2:$J$101,"<>Fermée",Anomalies!$J$2:$J$101,"<>Vérifiée")
A13: Mineure | B13: =COUNTIFS(Anomalies!$E$2:$E$101,"Mineure",Anomalies!$J$2:$J$101,"<>Fermée",Anomalies!$J$2:$J$101,"<>Vérifiée")
A15: Critère de sortie : 100 % exécuté et 0 anomalie bloquante non fermée.
A16: Recette prononçable ? | B16: =IF(AND(H7=1,B11=0),"OUI","NON")

Sheet Cas de test
A1: Catégorie | B1: ID | C1: Profil | D1: Cas de test | E1: Prérequis | F1: Étapes | G1: Résultat attendu | H1: Testeur | I1: Date | J1: Statut | K1: N° anomalie | L1: Commentaire
A2: Transverse | B2: TR-01 | C2: Tous | D2: Connexion valide | E2: Compte actif, 2FA configurée | F2: Ouvrir /comptes/connexion ; saisir e-mail et mot de passe ; saisir le code à 6 chiffres de l'application d'authentification | G2: Redirection vers l'espace du profil ; nom et espace affichés en haut à droite
A3: Transverse | B3: TR-02 | C3: Tous | D3: Connexion refusée | E3: — | F3: Saisir un mot de passe erroné plusieurs fois | G3: Message générique (sans dire si l'e-mail existe) ; verrouillage temporaire après plusieurs échecs ; aucun accès
A4: Transverse | B4: TR-03 | C4: Tous | D4: 2FA obligatoire à la première connexion | E4: Compte neuf sans 2FA | F4: Se connecter ; constater la redirection vers /comptes/double-authentification ; scanner le QR code avec Google Authenticator, Microsoft Authenticator ou l'app Mots de passe (iPhone) ; saisir le code | G4: Aucune autre page accessible tant que la 2FA n'est pas activée ; après validation, accès normal ; pas de bouton de désactivation
A5: Transverse | B5: TR-04 | C5: Tous | D5: Mot de passe oublié | E5: Boîte mail accessible | F5: /comptes/mot-de-passe-oublie ; saisir l'e-mail ; ouvrir le lien reçu ; définir un nouveau mot de passe | G5: Le lien n'apparaît JAMAIS à l'écran, uniquement dans l'e-mail ; même message que l'e-mail existe ou non ; lien inutilisable une seconde fois
A6: Transverse | B6: TR-05 | C6: Tous | D6: Déconnexion | E6: Connecté | F6: Menu utilisateur > Déconnexion ; bouton Précédent du navigateur | G6: Retour à la connexion ; aucune page protégée réaffichée
A7: Transverse | B7: TR-06 | C7: Tous | D7: Accès direct par URL | E7: Connecté avec un profil limité | F7: Saisir l'URL d'un écran non autorisé (ex. /administration/comptes-agents) | G7: Page « Accès refusé » ; aucune donnée affichée
A8: Transverse | B8: TR-07 | C8: Tous | D8: Cloisonnement des sociétés | E8: 2 comptes clients de sociétés différentes | F8: Avec la société A, copier l'URL d'un ticket ; l'ouvrir connecté avec la société B | G8: Accès refusé ; aucune donnée de A visible
A9: Transverse | B9: TR-08 | C9: Tous | D9: Langue FR / EN | E9: — | F9: Basculer FR ⇄ EN sur plusieurs écrans | G9: Tous les libellés traduits ; aucune clé technique (ex. « Dash.Title ») affichée
A10: Transverse | B10: TR-09 | C10: Tous | D10: Thème clair / sombre | E10: — | F10: Basculer le thème ; naviguer sur 3 pages ; provoquer une erreur de saisie | G10: Le thème choisi est conservé partout ; textes lisibles
A11: Transverse | B11: TR-10 | C11: Tous | D11: Pagination des tables | E11: Table de plus de 10 lignes | F11: Changer de page et de taille de page | G11: Compteur « x–y sur N » exact ; aucune ligne perdue ni dupliquée
A12: Transverse | B12: TR-11 | C12: Tous | D12: Filtre des tables | E12: Table remplie | F12: Saisir un numéro, un nom, une date (ex. 26/09/2026), avec et sans accents | G12: Seules les lignes correspondantes restent ; compteur « N sur M » ; effacer le filtre restaure la liste
A13: Transverse | B13: TR-12 | C13: Tous | D13: Horodatage | E13: Faire une action en notant l'heure réelle | F13: Consulter la liste, la chronologie et le journal d'audit correspondants | G13: Date ET heure au format JJ/MM/AAAA HH:mm, heure d'Abidjan, égale à l'heure réelle (± 1 min) ; journal d'audit à la seconde
... A25: Transverse | B25: TR-24 | C25: Tous | D25: Lien de mot de passe (validité 2 h) | E25: Lien « mot de passe oublié » reçu | F25: Utiliser le lien ; réutiliser le même lien ; utiliser un lien reçu il y a plus de 2 heures | G25: 1er usage : OK. Réutilisation ou lien > 2 h : message clair « lien expiré ou déjà utilisé », jamais « Invalid token »
A26: Parcours rôle | B26: R01-01 | C26: R01 Visiteur / prospect | D26: Demande d'ouverture de compte société | F26: /comptes/soumettre : remplir raison sociale, RCCM, contact ; déposer les pièces exigées | G26: Accusé de réception ; demande en attente chez l'administrateur (R18)
A27: Parcours rôle | B27: R01-02 | C27: R01 Visiteur / prospect | D27: Pièce obligatoire manquante | F27: Soumettre sans une pièce exigée | G27: Blocage avec un message qui nomme la pièce manquante
A28: Parcours rôle | B28: R01-03 | C28: R01 Visiteur / prospect | D28: Inscription transporteur | F28: /comptes/inscription-transporteur | G28: Demande enregistrée ; e-mail de confirmation
A29: Parcours rôle | B29: R01-04 | C29: R01 Visiteur / prospect | D29: Invitation collaborateur | F29: Ouvrir le lien /comptes/invitation/… reçu par e-mail ; définir le mot de passe ; configurer la 2FA | G29: Compte actif rattaché à la bonne société ; lien réutilisé refusé
A30: Parcours rôle | B30: R01-05 | C30: R01 Visiteur / prospect | D30: Demande de compte : identité structurée | F30: /comptes/soumettre : renseigner Raison sociale et N° RCCM (ex. « ci abj 2024 b 12345 ») | G30: Demande acceptée ; RCCM normalisé en CI-ABJ-2024-B-12345
A31: Parcours rôle | B31: R01-06 | C31: R01 Visiteur / prospect | D31: RCCM invalide ou déjà utilisé | F31: Soumettre avec un RCCM mal formé, puis avec le RCCM d'une société existante | G31: Refus avec message clair ; aucun compte utilisateur orphelin créé (l'e-mail reste réutilisable)
A32: Parcours rôle | B32: R01-07 | C32: R01 Visiteur / prospect | D32: Menu et accès interdit | F32: Vérifier le menu ; saisir l'URL d'un écran d'un autre profil | G32: Menu limité au profil ; écran étranger refusé
A33: Parcours rôle | B33: R02-01 | C33: R02 Client — utilisateur société | D33: Tableau de bord | F33: /client/dashboard | G33: Indicateurs limités à la société de l'utilisateur
A34: Parcours rôle | B34: R02-02 | C34: R02 Client — utilisateur société | D34: Soumettre une demande Import | F34: Créer un dossier Import avec un BL ; déposer les documents | G34: Numéros de dossier et de ticket attribués ; statut « Soumis » horodaté
A35: Parcours rôle | B35: R02-03 | C35: R02 Client — utilisateur société | D35: Soumettre une demande Export | F35: Créer un dossier Export avec un booking | G35: Dossier créé et orienté vers le Back Office Export
A36: Parcours rôle | B36: R02-04 | C36: R02 Client — utilisateur société | D36: Suivre ses demandes | F36: /client/demandes : filtrer, paginer, ouvrir un dossier | G36: Chronologie complète et horodatée ; statut à jour
A37: Parcours rôle | B37: R02-05 | C37: R02 Client — utilisateur société | D37: Répondre à un complément | F37: Ticket « En attente client » : ajouter un message et une pièce | G37: Le ticket revient chez l'agent ; le SLA reprend
... A140: Bout en bout | B140: E2E-08 | C140: Plusieurs | D140: Nouvel agent | F140: R18 crée l'agent → première connexion avec 2FA obligatoire → l'agent ne voit que ses écrans | G140: Aucun écran hors permissions ; accès direct par URL refusé

Sheet Anomalies
A1: N° anomalie | B1: Cas de test | C1: Date constat | D1: Testeur | E1: Sévérité | F1: URL | G1: Étapes pour reproduire | H1: Résultat attendu | I1: Résultat obtenu | J1: Statut | K1: Date re-test | L1: Re-test OK ?
